{
  "name": "Dawn",
  "level": {
    "Controlled": "Level5"
  },
  "school": {
    "Controlled": "Evocation"
  },
  "is_ritual": false,
  "casting_time": {
    "Controlled": {
      "Actions": 1
    }
  },
  "range": {
    "Controlled": {
      "Dist": {
        "Feet": 60
      }
    }
  },
  "has_v_component": true,
  "has_s_component": true,
  "m_components": "a suburst pendant worth at least 100 gp",
  "duration": {
    "Controlled": {
      "Minutes": [
        1,
        true
      ]
    }
  },
  "description": "The light of dawn shines down on a location you specify within range. Until the spell ends, a 30-foot-radius, 40-foot-high cylinder of bright light glimmers there. This light is sunlight.\nWhen the cylinder appears, each creature in it must make a Constitution saving throw, taking 4d10 radiant damage on a failed save, or half as much damage on a successful one. A creature must also make this saving throw whenever it ends its turn in the cylinder.\nIf you’re within 60 feet of the cylinder, you can move it up to 60 feet as a bonus action on your turn.",
  "upcast_description": null,
  "tables": []
}